nonebot_plugin_servicestate/__init__.py
nonebot_plugin_servicestate/exception.py
nonebot_plugin_servicestate/manager.py
nonebot_plugin_servicestate/protocol/__init__.py
nonebot_plugin_servicestate/protocol/demo.py
nonebot_plugin_servicestate/protocol/http.py
nonebot_plugin_servicestate/protocol/protocol.py
nonebot_plugin_servicestate/protocol/tcp.py
nonebot_plugin_servicestate/service.py
nonebot_plugin_servicestate/utils.py
nonebot_plugin_servicestate-0.2.1.dist-info/LICENSE
nonebot_plugin_servicestate-0.2.1.dist-info/METADATA
nonebot_plugin_servicestate-0.2.1.dist-info/WHEEL
nonebot_plugin_servicestate-0.2.1.dist-info/RECORD
