Metadata-Version: 2.1
Name: nonebot-plugin-servicestate
Version: 0.2.1
Summary: 基于NoneBot2的状态监测插件
Home-page: https://github.com/OREOCODEDEV/nonebot-plugin-servicestate
License: MIT
Author: OREOCODEDEV
Author-email: 17620745509@126.COM
Requires-Python: >=3.8,<4.0
Classifier: License :: OSI Approved :: MIT License
Classifier: Programming Language :: Python :: 3
Classifier: Programming Language :: Python :: 3.8
Classifier: Programming Language :: Python :: 3.9
Classifier: Programming Language :: Python :: 3.10
Classifier: Programming Language :: Python :: 3.11
Requires-Dist: httpx (>=0.20)
Requires-Dist: nonebot-adapter-onebot (>=2.1.0,<3.0.0)
Requires-Dist: nonebot-plugin-localstore (>=0.2.0)
Requires-Dist: nonebot2 (>=2.0.0,<3.0.0)
Requires-Dist: pydantic (>=1.10.2,<2.0.0)
Project-URL: Repository, https://github.com/OREOCODEDEV/nonebot-plugin-servicestate
